nekkar/__init__.py
nekkar/core/__init__.py
nekkar/core/cache.py
nekkar/core/exceptions.py
nekkar/core/limiter.py
nekkar/core/storage.py
nekkar/examples/__init__.py
nekkar/tests/__init__.py
nekkar/tests/integration/__init__.py
nekkar/tests/integration/test_cache.py
nekkar/tests/manual/__init__.py
nekkar/tests/manual/report.py
nekkar/tests/manual/test_concurrency.py
nekkar/tests/manual/test_interface.py
nekkar/tests/unit/__init__.py
nekkar/tests/unit/test_cache.py
nekkar/tests/unit/test_nekkar.py
nekkar/tests/unit/test_storage.py
nekkar-0.0.1.dist-info/LICENSE
nekkar-0.0.1.dist-info/METADATA
nekkar-0.0.1.dist-info/WHEEL
nekkar-0.0.1.dist-info/top_level.txt
nekkar-0.0.1.dist-info/RECORD
