Metadata-Version: 2.1
Name: nekkar
Version: 0.0.1
Summary: Rate limiter
Home-page: https://github.com/hovodab/nekkar
Author: Hovhannes Dabaghyan
Author-email: hovhannes.dabaghyan@gmail.com
License: UNKNOWN
Project-URL: Bug Tracker, https://github.com/hovodab/nekkar/issues
Platform: UNKNOWN
Classifier: Programming Language :: Python :: 3
Classifier: License :: OSI Approved :: MIT License
Classifier: Operating System :: OS Independent
Requires-Python: >=3.6
License-File: LICENSE
Requires-Dist: pymemcache (==3.5.0)
